CHANGES.txt
LICENSE.txt
MANIFEST.in
README.txt
setup.py
SimpleCache.egg-info/PKG-INFO
SimpleCache.egg-info/SOURCES.txt
SimpleCache.egg-info/dependency_links.txt
SimpleCache.egg-info/top_level.txt
simplecache/__init__.py
simplecache/simplecache.py