Metadata-Version: 1.0
Name: SimpleCache
Version: 0.1.1
Summary: A simple time- and size-based in-memory cache, both threadsafe and non-threadsafe.
Home-page: http://pypi.python.org/pypi/SimpleCache/
Author: Scott Bonneau
Author-email: scott.bonneau@gmail.com
License: LICENSE.txt
Platform: UNKNOWN
